{
  "title": "Місто тіней",
  "poster": "poster8",
  "description": "Опис: Детектив у великому місті розслідує серію зникнень, які пов'язані з таємничою організацією. Він виявляє, що місто приховує темні таємниці, які можуть змінити його назавжди.",
  "duration": 180,
  "schedule": [
    {
      "date": "22.06.2024",
      "times": ["11:00-14:00", "15:00-18:00", "19:00-22:00"]
    },
    {
      "date": "23.06.2024",
      "times": ["11:00-14:00", "15:00-18:00", "19:00-22:00"]
    },
    {
      "date": "24.06.2024",
      "times": ["11:00-14:00", "15:00-18:00", "19:00-22:00"]
    }
  ]
}
